PyUI3/__init__.py
PyUI3/test.py
pyui3-5.3.0.dist-info/WHEEL
pyui3-5.3.0.dist-info/METADATA
pyui3-5.3.0.dist-info/RECORD
