Metadata-Version: 2.1
Name: PyUI3
Version: 5.3.0
Summary: WinUI3 with Python!
Author-email: Johnny Konczal <johndrostan@outlook.com>
Requires-Dist: win32more
Requires-Dist: tk
